monobank/__init__.py
monobank/_core/__init__.py
monobank/_core/client/__init__.py
monobank/_core/client/acquiring.py
monobank/_core/client/base.py
monobank/_core/serializers.py
monobank/api/__init__.py
monobank/api/_acquiring/__init__.py
monobank/api/_acquiring/_merchant/__init__.py
monobank/api/_acquiring/_merchant/details.py
monobank/api/_acquiring/_merchant/invoice.py
monobank/api/_acquiring/_merchant/pubkey.py
monobank/api/_acquiring/_merchant/qr.py
monobank/api/_acquiring/_merchant/statement.py
monobank/api/_acquiring/_merchant/submerchant.py
monobank/api/_acquiring/_merchant/wallet.py
monobank_tool-0.1.5.dist-info/LICENSE
monobank_tool-0.1.5.dist-info/METADATA
monobank_tool-0.1.5.dist-info/WHEEL
monobank_tool-0.1.5.dist-info/RECORD
